zensols/clinicamr/resources/adm-selection.conf
zensols/clinicamr/resources/app.conf
zensols/clinicamr/resources/default.conf
zensols/clinicamr/resources/obj.yml
zensols/clinicamr/resources/mimic/note-selection.csv
zensols/clinicamr/resources/mimic/section-selection.csv
zensols/clinicamr/__init__.py
zensols/clinicamr/adm.py
zensols/clinicamr/app.py
zensols/clinicamr/cli.py
zensols/clinicamr/decorator.py
zensols/clinicamr/domain.py
zensols/clinicamr/parafac.py
zensols/clinicamr/proto.py
zensols/clinicamr/spring.py
zensols_clinicamr-0.1.1.dist-info/METADATA
zensols_clinicamr-0.1.1.dist-info/WHEEL
zensols_clinicamr-0.1.1.dist-info/entry_points.txt
zensols_clinicamr-0.1.1.dist-info/licenses/LICENSE.md
zensols_clinicamr-0.1.1.dist-info/RECORD
