Metadata-Version: 2.3
Name: zensols_clinicamr
Version: 0.1.1
Summary: This package parses clinical notes in to Abstract Meaning Representation Graphs (AMR).
Project-URL: Homepage, https://github.com/plandes/clinicamr
Project-URL: Documentation, https://plandes.github.io/clinicamr
Project-URL: Repository, https://github.com/plandes/clinicamr.git
Project-URL: Issues, https://github.com/plandes/clinicamr/issues
Project-URL: Changelog, https://github.com/plandes/clinicamr/blob/master/CHANGELOG.md
Author-email: Paul Landes <landes@mailc.net>
License: MIT
Keywords: tooling
Requires-Python: <3.13,>=3.11
Requires-Dist: zensols-amrspring~=0.1.0
Requires-Dist: zensols-amr~=v0.2.6
Requires-Dist: zensols-dbpg~=1.4.0
Requires-Dist: zensols-mimicsid~=v1.10.1
